README.md
setup.py
confparser/__init__.py
confparser/parser.py
confparser.egg-info/PKG-INFO
confparser.egg-info/SOURCES.txt
confparser.egg-info/dependency_links.txt
confparser.egg-info/requires.txt
confparser.egg-info/top_level.txt
tests/__init__.py
tests/test_parser.py