Metadata-Version: 2.1
Name: confparser
Version: 0.1.6
Summary: Python config parser library
Home-page: https://github.com/teamhide/confparser
Author: teamhide
Author-email: padocon@naver.com
License: UNKNOWN
Download-URL: https://pypi.python.org/pypi/confparser
Platform: UNKNOWN
Classifier: Intended Audience :: Developers
Classifier: Programming Language :: Python
Classifier: Programming Language :: Python :: 3.4
Classifier: Programming Language :: Python :: 3.5
Classifier: Programming Language :: Python :: 3.6
Classifier: Programming Language :: Python :: 3.7
Classifier: Programming Language :: Python :: 3.8
Classifier: License :: OSI Approved :: MIT License
Classifier: Operating System :: OS Independent
Requires-Python: >=3.4
